<?xml version="1.0" encoding="utf-8"?>
<class id="03baf551-4044-4cc2-b98d-a1f54d3df58e" type="Folder" typeId="3407a825-1331-4f3f-89a4-901903ed97ce">
  <name>Configuration</name>
  <display>Configuration</display>
  <isAbstract>false</isAbstract>
  <genericTypes />
  <isMapped>false</isMapped>
  <parentFolderId>21f893a1-27b5-44ea-86fa-15df898dba03</parentFolderId>
  <stereotypes />
  <metadata />
  <childElements>
    <childElement id="179b5dac-61cb-46f6-a3e3-4a81b64e3212" type="Template Output" typeId="d421c322-7a51-4094-89fa-e5d8a0a97b27">
      <name>Intent.AspNetCore.HealthChecks.HealthChecksConfiguration</name>
      <display>Intent.AspNetCore.HealthChecks.HealthChecksConfiguration</display>
      <externalReference>Intent.AspNetCore.HealthChecks</externalReference>
      <isAbstract>false</isAbstract>
      <genericTypes />
      <isMapped>false</isMapped>
      <parentFolderId>03baf551-4044-4cc2-b98d-a1f54d3df58e</parentFolderId>
      <stereotypes />
      <metadata>
        <entry key="status" value="assigned" />
      </metadata>
      <childElements />
    </childElement>
    <childElement id="d8058bbd-e720-4d13-8e03-763c0303f4ea" type="Template Output" typeId="d421c322-7a51-4094-89fa-e5d8a0a97b27">
      <name>Intent.AspNetCore.Versioning.ApiVersioningConfiguration</name>
      <display>Intent.AspNetCore.Versioning.ApiVersioningConfiguration</display>
      <externalReference>Intent.AspNetCore.Versioning</externalReference>
      <isAbstract>false</isAbstract>
      <genericTypes />
      <isMapped>false</isMapped>
      <parentFolderId>03baf551-4044-4cc2-b98d-a1f54d3df58e</parentFolderId>
      <stereotypes />
      <metadata>
        <entry key="status" value="assigned" />
      </metadata>
      <childElements />
    </childElement>
    <childElement id="317a91bc-99a5-4b6e-965a-c2277080c32f" type="Template Output" typeId="d421c322-7a51-4094-89fa-e5d8a0a97b27">
      <name>Intent.AspNetCore.Versioning.ApiVersionSwaggerGenOptions</name>
      <display>Intent.AspNetCore.Versioning.ApiVersionSwaggerGenOptions</display>
      <externalReference>Intent.AspNetCore.Versioning</externalReference>
      <isAbstract>false</isAbstract>
      <genericTypes />
      <isMapped>false</isMapped>
      <parentFolderId>03baf551-4044-4cc2-b98d-a1f54d3df58e</parentFolderId>
      <stereotypes />
      <metadata>
        <entry key="status" value="assigned" />
      </metadata>
      <childElements />
    </childElement>
    <childElement id="3fc94114-80fd-49a9-90b8-9fa693f902ac" type="Template Output" typeId="d421c322-7a51-4094-89fa-e5d8a0a97b27">
      <name>Intent.Bugsnag.BugsnagConfiguration</name>
      <display>Intent.Bugsnag.BugsnagConfiguration</display>
      <externalReference>Intent.Bugsnag</externalReference>
      <isAbstract>false</isAbstract>
      <genericTypes />
      <isMapped>false</isMapped>
      <parentFolderId>03baf551-4044-4cc2-b98d-a1f54d3df58e</parentFolderId>
      <stereotypes />
      <metadata>
        <entry key="status" value="assigned" />
      </metadata>
      <childElements />
    </childElement>
    <childElement id="6a588988-886c-46f5-a647-bbc37a6e7612" type="Template Output" typeId="d421c322-7a51-4094-89fa-e5d8a0a97b27">
      <name>Intent.AspNetCore.Swashbuckle.SwashbuckleConfiguration</name>
      <display>Intent.AspNetCore.Swashbuckle.SwashbuckleConfiguration</display>
      <externalReference>Intent.AspNetCore.Swashbuckle</externalReference>
      <isAbstract>false</isAbstract>
      <genericTypes />
      <isMapped>false</isMapped>
      <parentFolderId>03baf551-4044-4cc2-b98d-a1f54d3df58e</parentFolderId>
      <stereotypes />
      <metadata>
        <entry key="status" value="assigned" />
      </metadata>
      <childElements />
    </childElement>
    <childElement id="3342fb10-889c-4e62-8d1e-341b9d7e2c81" type="Template Output" typeId="d421c322-7a51-4094-89fa-e5d8a0a97b27">
      <name>Intent.Dapr.AspNetCore.DaprConfiguration</name>
      <display>Intent.Dapr.AspNetCore.DaprConfiguration</display>
      <externalReference>Intent.Dapr.AspNetCore</externalReference>
      <isAbstract>false</isAbstract>
      <genericTypes />
      <isMapped>false</isMapped>
      <parentFolderId>03baf551-4044-4cc2-b98d-a1f54d3df58e</parentFolderId>
      <stereotypes />
      <metadata>
        <entry key="status" value="assigned" />
      </metadata>
      <childElements />
    </childElement>
    <childElement id="9e483383-0862-4e61-8339-0d24fc7bb21b" type="Template Output" typeId="d421c322-7a51-4094-89fa-e5d8a0a97b27">
      <name>Intent.AspNetCore.ProblemDetailsConfiguration</name>
      <display>Intent.AspNetCore.ProblemDetailsConfiguration</display>
      <externalReference>Intent.AspNetCore</externalReference>
      <isAbstract>false</isAbstract>
      <genericTypes />
      <isMapped>false</isMapped>
      <parentFolderId>03baf551-4044-4cc2-b98d-a1f54d3df58e</parentFolderId>
      <stereotypes />
      <metadata>
        <entry key="status" value="assigned" />
      </metadata>
      <childElements />
    </childElement>
    <childElement id="0934f966-7e93-4dee-b897-45f508c0cf96" type="Template Output" typeId="d421c322-7a51-4094-89fa-e5d8a0a97b27">
      <name>Intent.Application.Identity.ApplicationSecurityConfiguration</name>
      <display>Intent.Application.Identity.ApplicationSecurityConfiguration</display>
      <externalReference>Intent.Application.Identity</externalReference>
      <isAbstract>false</isAbstract>
      <genericTypes />
      <isMapped>false</isMapped>
      <parentFolderId>03baf551-4044-4cc2-b98d-a1f54d3df58e</parentFolderId>
      <stereotypes />
      <metadata>
        <entry key="status" value="assigned" />
      </metadata>
      <childElements />
    </childElement>
  </childElements>
</class>